bequem/__init__.py
bequem/block_encoding.py
bequem/qsp.py
bequem-0.0.0.dist-info/METADATA
bequem-0.0.0.dist-info/WHEEL
bequem-0.0.0.dist-info/top_level.txt
bequem-0.0.0.dist-info/RECORD
