Metadata-Version: 2.2
Name: bequem
Version: 0.0.0
Summary: A tool to construct and simulate block encodings for quantum computation
Author-email: Matthias Deiml <matthias.deiml@uni-a.de>
Project-URL: Repository, https://github.com/bequem-py/bequem.git
Keywords: quantum computing
